{
    "filename": "2022-09-0901.php",
    "type": "php",
    "size": 107,
    "md5": "41a93270fb72a27923ecfef470029542",
    "connection": {
        "method": "POST",
        "password": "a",
        "param_name": "cmd",
        "encoding": "base64",
        "test_command": "echo 'test';"
    },
    "features": {
        "file_upload": false,
        "command_exec": false,
        "database_ops": false,
        "eval_usage": false,
        "obfuscated": true
    },
    "detection": {
        "antivirus_score": 0,
        "yara_rules": []
    },
    "metadata": {
        "discovered_date": "2025-04-25",
        "last_tested": "2025-04-25",
        "working_status": true,
        "original_filename": "2022-09-0901.php",
        "source_path": "uncheck-shells/2022-09-0901.php"
    }
}